dataeval_plots/__init__.py
dataeval_plots/_registry.py
dataeval_plots/_version.py
dataeval_plots/protocols.py
dataeval_plots/py.typed
dataeval_plots/backends/__init__.py
dataeval_plots/backends/_altair.py
dataeval_plots/backends/_base.py
dataeval_plots/backends/_matplotlib.py
dataeval_plots/backends/_plotly.py
dataeval_plots/backends/_seaborn.py
dataeval_plots/backends/_shared.py
dataeval_plots-0.0.5.dist-info/METADATA
dataeval_plots-0.0.5.dist-info/WHEEL
dataeval_plots-0.0.5.dist-info/RECORD
