Metadata-Version: 2.4
Name: dataeval-plots
Version: 0.0.5
Summary: DataEval companion package for plotting utilities
Project-URL: Homepage, https://dataeval.ai/
Project-URL: Repository, https://github.com/aria-ml/dataeval/
Project-URL: Documentation, https://dataeval.readthedocs.io/
Author-email: Andrew Weng <andrew.weng@ariacoustics.com>, Ryan Wood <ryan.wood@ariacoustics.com>, Shaun Jullens <shaun.jullens@ariacoustics.com>
Maintainer-email: ARiA <dataeval@ariacoustics.com>
License-Expression: MIT
Classifier: Development Status :: 4 - Beta
Classifier: Intended Audience :: Science/Research
Classifier: License :: OSI Approved :: MIT License
Classifier: Operating System :: OS Independent
Classifier: Programming Language :: Python :: 3 :: Only
Classifier: Programming Language :: Python :: 3.10
Classifier: Programming Language :: Python :: 3.11
Classifier: Programming Language :: Python :: 3.12
Classifier: Programming Language :: Python :: 3.13
Classifier: Topic :: Scientific/Engineering
Requires-Python: <3.14,>=3.10
Requires-Dist: matplotlib>=3.7.1
Requires-Dist: numpy>=1.24.2; python_version < '3.12'
Requires-Dist: numpy>=1.26.2; python_version >= '3.12'
Requires-Dist: polars>=1.0.0
Provides-Extra: all
Requires-Dist: altair>=5.0; extra == 'all'
Requires-Dist: plotly>=5.0; extra == 'all'
Requires-Dist: seaborn>=0.12; extra == 'all'
Provides-Extra: altair
Requires-Dist: altair>=5.0; extra == 'altair'
Provides-Extra: opencv
Requires-Dist: opencv-python-headless>=4.12.0.88; extra == 'opencv'
Provides-Extra: plotly
Requires-Dist: plotly>=5.0; extra == 'plotly'
Provides-Extra: seaborn
Requires-Dist: seaborn>=0.12; extra == 'seaborn'
